recomb_to_s3/__init__.py
recomb_to_s3/admin.py
recomb_to_s3/apps.py
recomb_to_s3/contrib.py
recomb_to_s3/migrations/0001_initial.py
recomb_to_s3/migrations/__init__.py
recomb_to_s3/models.py
recomb_to_s3/tests.py
recomb_to_s3/urls.py
recomb_to_s3/utils.py
recomb_to_s3/views.py
recomb_to_s3-0.1.3.dist-info/WHEEL
recomb_to_s3-0.1.3.dist-info/METADATA
recomb_to_s3-0.1.3.dist-info/RECORD
