Metadata-Version: 2.1
Name: recomb-to-s3
Version: 0.1.3
Summary: package to save files in s3 in a simple way.
Author: alexandrejastrow
Author-email: alexandre.jastrow@gmail.com
Requires-Python: >=3.10,<4.0
Classifier: Programming Language :: Python :: 3
Classifier: Programming Language :: Python :: 3.10
Classifier: Programming Language :: Python :: 3.11
Requires-Dist: boto3 (>=1.26.47,<2.0.0)
Requires-Dist: django (>=4.1.5,<5.0.0)
Requires-Dist: django-storages (>=1.13.2,<2.0.0)
